festin/__init__.py
festin/__main__.py
festin/analysis.py
festin/black_list.py
festin/events.py
festin/logo.py
festin/redis.py
festin/s3.py
festin/utils.py
festin-0.0.16.dist-info/LICENSE
festin-0.0.16.dist-info/METADATA
festin-0.0.16.dist-info/WHEEL
festin-0.0.16.dist-info/entry_points.txt
festin-0.0.16.dist-info/top_level.txt
festin-0.0.16.dist-info/zip-safe
festin-0.0.16.dist-info/RECORD
