Metadata-Version: 2.1
Name: festin
Version: 0.0.16
Summary: Festin is a powered S3 bucket finder and content discover
Home-page: https://github.com/cr0hn/festin
License: License :: OSI Approved :: BSD License
Platform: UNKNOWN
Classifier: Programming Language :: Python :: 3.8
Requires-Python: >=3.8
Requires-Dist: lxml
Requires-Dist: aiofiles
Requires-Dist: aioredis
Requires-Dist: watchgod
Requires-Dist: async-dns
Requires-Dist: aiohttp
Requires-Dist: aiohttp-proxy
Requires-Dist: colorama
Requires-Dist: filetype
